dbt/adapters/__init__.py
dbt/adapters/risingwave/__init__.py
dbt/adapters/risingwave/__version__.py
dbt/adapters/risingwave/connections.py
dbt/adapters/risingwave/impl.py
dbt/adapters/risingwave/relation.py
dbt/adapters/risingwave/relation_configs/__init__.py
dbt/adapters/risingwave/relation_configs/index.py
dbt/adapters/risingwave/relation_configs/materialized_view.py
dbt/include/risingwave/__init__.py
dbt/include/risingwave/dbt_project.yml
dbt/include/risingwave/profile_template.yml
dbt/include/risingwave/macros/adapters.sql
dbt/include/risingwave/macros/catalog.sql
dbt/include/risingwave/macros/materializations/incremental.sql
dbt/include/risingwave/macros/materializations/materialized_view.sql
dbt/include/risingwave/macros/materializations/materializedview.sql
dbt/include/risingwave/macros/materializations/sink.sql
dbt/include/risingwave/macros/materializations/source.sql
dbt/include/risingwave/macros/materializations/table.sql
dbt/include/risingwave/macros/materializations/table_with_connector.sql
dbt/include/risingwave/macros/materializations/view.sql
dbt_risingwave-1.9.7.dist-info/licenses/LICENSE
dbt_risingwave-1.9.7.dist-info/METADATA
dbt_risingwave-1.9.7.dist-info/WHEEL
dbt_risingwave-1.9.7.dist-info/top_level.txt
dbt_risingwave-1.9.7.dist-info/RECORD
