Metadata-Version: 2.4
Name: dbt-risingwave
Version: 1.9.7
Summary: The RisingWave adapter plugin for dbt
Home-page: https://github.com/risingwavelabs/dbt-risingwave
Author: Dylan Chen
Author-email: zilin@risingwave-labs.com
License: http://www.apache.org/licenses/LICENSE-2.0
Keywords: dbt RisingWave
Classifier: Development Status :: 5 - Production/Stable
Classifier: License :: OSI Approved :: Apache Software License
Classifier: Operating System :: Microsoft :: Windows
Classifier: Operating System :: MacOS :: MacOS X
Classifier: Operating System :: POSIX :: Linux
Classifier: Programming Language :: Python :: 3.9
Classifier: Programming Language :: Python :: 3.10
Classifier: Programming Language :: Python :: 3.11
Classifier: Programming Language :: Python :: 3.12
Classifier: Programming Language :: Python :: 3.13
Requires-Python: >=3.9
License-File: LICENSE
Requires-Dist: dbt-postgres~=1.9.0
Requires-Dist: dbt-core~=1.9.0
Requires-Dist: dbt-common<2.0,>=1.0.4
Requires-Dist: dbt-adapters<2.0,>=1.7.0
Dynamic: author
Dynamic: author-email
Dynamic: classifier
Dynamic: description
Dynamic: description-content-type
Dynamic: home-page
Dynamic: keywords
Dynamic: license
Dynamic: license-file
Dynamic: requires-dist
Dynamic: requires-python
Dynamic: summary
